bootpeg/__init__.py
bootpeg/api.py
bootpeg/utility.py
bootpeg/grammars/__init__.py
bootpeg/grammars/bpeg.bpeg
bootpeg/grammars/bpeg.py
bootpeg/grammars/peg.bpeg
bootpeg/grammars/peg.py
bootpeg/pika/__init__.py
bootpeg/pika/act.py
bootpeg/pika/boot.bpeg
bootpeg/pika/boot.py
bootpeg/pika/front.py
bootpeg/pika/peg.py
bootpeg-0.6.0.dist-info/LICENSE
bootpeg-0.6.0.dist-info/WHEEL
bootpeg-0.6.0.dist-info/METADATA
bootpeg-0.6.0.dist-info/RECORD
