Metadata-Version: 2.1
Name: bootpeg
Version: 0.6.0
Summary: bootpeg – the bootstrapping PEG parser
Home-page: https://github.com/maxfischer2781/bootpeg
Keywords: parser peg pep617
Author: Max Fischer
Author-email: maxfischer2781@gmail.com
Classifier: Intended Audience :: Developers
Classifier: License :: OSI Approved :: MIT License
Classifier: Programming Language :: Python :: 3 :: Only
Requires-Dist: typing_extensions
Requires-Dist: importlib_resources
Requires-Dist: sphinx ; extra == "doc"
Requires-Dist: pytest ; extra == "test"
Requires-Dist: flake8 ; extra == "test"
Requires-Dist: flake8-bugbear ; extra == "test"
Requires-Dist: black ; extra == "test" and ( implementation_name=='cpython')
Requires-Dist: coverage ; extra == "test"
Requires-Dist: pytest-cov ; extra == "test"
Provides-Extra: doc
Provides-Extra: test
